KUtils/classifier/generic_classifier_utils.py
KUtils/cluster/pca_util.py
KUtils/common/KeshLabelEncoder.py
KUtils/common/blend_util.py
KUtils/common/utils.py
KUtils/eda/chartil.py
KUtils/eda/data_preparation.py
KUtils/kalgo/aubo.py
KUtils/linear_regression/auto_linear_regression.py
KUtils/linear_regression/clustered_linear_regression.py
KUtils/logistic_regression/auto_logistic_regression.py
KUtils/logistic_regression/clustered_logistic_regression.py
KUtils/stat/statil.py
kesh_utils-0.4.9.dist-info/LICENSE
kesh_utils-0.4.9.dist-info/METADATA
kesh_utils-0.4.9.dist-info/WHEEL
kesh_utils-0.4.9.dist-info/top_level.txt
kesh_utils-0.4.9.dist-info/RECORD
