Metadata-Version: 2.1
Name: kesh-utils
Version: 0.4.9
Summary: Kesh Utils for Data science/EDA/Data preparation 
Home-page: https://github.com/KeshavShetty/kesh-utils
Author: Keshav Shetty
Author-email: keshavshetty@gmail.com
License: MIT
Platform: UNKNOWN
Classifier: License :: OSI Approved :: MIT License
Classifier: Programming Language :: Python
Classifier: Programming Language :: Python :: 2
Classifier: Programming Language :: Python :: 3
